easyCorpus/__init__.py
easyCorpus/easyCorpus.py
easyCorpus-2.3.dist-info/.ipynb_checkpoints/PKG-INFO-checkpoint
easyCorpus-2.3.dist-info/.ipynb_checkpoints/dependency_links-checkpoint.txt
easyCorpus-2.3.dist-info/LICENSE
easyCorpus-2.3.dist-info/METADATA
easyCorpus-2.3.dist-info/WHEEL
easyCorpus-2.3.dist-info/top_level.txt
easyCorpus-2.3.dist-info/RECORD
